[
    {
    "type": "function",
        "function": {
            "name": "search",
            "description": "This function MUST be called whenever the user asks to 'find' or 'search' (including Vietnamese 'tìm' or 'tìm kiếm') for the presence of an object. It scans through the video frames and identifies the exact frames in which the specified object appears. The function maps the object to all matching frames in the correct temporal order.",
            "parameters": {
                "type": "object",
                "properties": {
                    "keyword": {
                        "type": "array",
                        "items": {
                            "type": "string"
                        },
                        "description": "An ordered list of keywords containing object, object's action, places, situation, each represented as a string only english. (e.g., 'Every morning, the woman runs in the park' -> ['woman', 'runs', 'park, 'morning'])"
                    }
                },
                "required": ["keyword"],
                "additionalProperties": false
            }
        }
    },

    {
    "type": "function",
        "function": {
            "name": "find_flow",
            "description": "This function MUST be called whenever the user asks to 'find' or 'search' (including Vietnamese 'tìm' or 'tìm kiếm') for key states, moments, or phases of an action. It searches and identifies the exact frames corresponding to a sequence of key states within an action. The function maps each state to its matching frame in the correct temporal order. (e.g., steps in a dance, or phases in a high jump). The function maps each state to its matching frame in the correct temporal order.",
            "parameters": {
                "type": "object",
                "properties": {
                    "state": {
                        "type": "array",
                        "items": {
                            "type": "string"
                        },
                        "description": "An ordered list of key states or moments of the action, each represented as a string only english."
                    }
                },
                "required": ["state"],
                "additionalProperties": false
            }
        }   
    }
]
